cli_password_generator/__init__.py
cli_password_generator/main.py
cli_password_generator-0.1.0.dist-info/METADATA
cli_password_generator-0.1.0.dist-info/WHEEL
cli_password_generator-0.1.0.dist-info/entry_points.txt
cli_password_generator-0.1.0.dist-info/RECORD
