Metadata-Version: 2.1
Name: cli-password-generator
Version: 0.1.0
Summary: A CLI password generator
Author: Giorgos Kallis
Author-email: giorgos.kallis.gr@gmail.com
Requires-Python: >=3.11,<4.0
Classifier: Programming Language :: Python :: 3
Classifier: Programming Language :: Python :: 3.11
Requires-Dist: typer[all] (>=0.9.0,<0.10.0)
